{
  "wall_posts_sent_to_you": [
    {
      "timestamp": 1510162159,
      "data": [
        {
          "post": "Hbu"
        }
      ],
      "title": "Yash Shah wrote on your timeline."
    },
    {
      "timestamp": 1510113618,
      "data": [
        {
          "post": "Happy birthday Shubhanshi"
        }
      ],
      "title": "Leena Mukesh Mehta wrote on your timeline."
    },
    {
      "timestamp": 1510059816,
      "data": [
        {
          "post": "Happy birthday"
        }
      ],
      "title": "Amar Parab wrote on your timeline."
    },
    {
      "timestamp": 1510058756,
      "data": [
        {
          "post": "Appy bday beta"
        }
      ],
      "title": "Cma Manish wrote on your timeline."
    },
    {
      "timestamp": 1510054527,
      "data": [
        {
          "post": "Happy Birthday \u00f0\u009f\u008e\u0082"
        }
      ],
      "title": "Sara Sabuwala wrote on your timeline."
    },
    {
      "timestamp": 1510047699,
      "title": "Sandhya Shah wrote on your timeline."
    },
    {
      "timestamp": 1510040716,
      "data": [
        {
          "post": "Happy birthday"
        }
      ],
      "title": "Rishabh Joshi wrote on your timeline."
    },
    {
      "timestamp": 1510034301,
      "data": [
        {
          "post": "Happy Birthday Dear Shubhanshi"
        }
      ],
      "title": "Grishma Agrawal wrote on your timeline."
    },
    {
      "timestamp": 1510033630,
      "data": [
        {
          "post": "many many happy returns of the day"
        }
      ],
      "title": "Purviish Shah wrote on your timeline."
    },
    {
      "timestamp": 1510033143,
      "data": [
        {
          "post": "Happy birthday \u00f0\u009f\u008e\u0082"
        }
      ],
      "title": "Yash Tambe wrote on your timeline."
    },
    {
      "timestamp": 1510032799,
      "data": [
        {
          "post": "Happy Birthday..wish u make this day a memorable one.."
        }
      ],
      "title": "Parth Tade wrote on your timeline."
    },
    {
      "timestamp": 1510032684,
      "data": [
        {
          "post": "Happy birthday"
        }
      ],
      "title": "Soham Joglekar wrote on your timeline."
    },
    {
      "timestamp": 1510032415,
      "data": [
        {
          "post": "Happy birthday dear\u00f0\u009f\u008e\u0082\u00f0\u009f\u008e\u0089\u00f0\u009f\u008e\u0089\u00f0\u009f\u008e\u0089\u00f0\u009f\u008c\u00b7GBU"
        }
      ],
      "title": "Shalu Goel wrote on your timeline."
    },
    {
      "timestamp": 1510031926,
      "data": [
        {
          "post": "Happy Birthday"
        }
      ],
      "title": "Rishi Polke wrote on your timeline."
    },
    {
      "timestamp": 1510030842,
      "data": [
        {
          "post": "Happy Birthday..."
        }
      ],
      "title": "Drigesh Mittal wrote on your timeline."
    },
    {
      "timestamp": 1510030623,
      "data": [
        {
          "post": "Happy Birthday!!"
        }
      ],
      "title": "Param Vora wrote on your timeline."
    },
    {
      "timestamp": 1510030478,
      "data": [
        {
          "post": "Happy birthday :)"
        }
      ],
      "title": "Ritu Agrawal Gupta wrote on your timeline."
    },
    {
      "timestamp": 1510028830,
      "data": [
        {
          "post": "Happy Birthday"
        }
      ],
      "title": "Parth Samant wrote on your timeline."
    },
    {
      "timestamp": 1510028219,
      "data": [
        {
          "post": "Happy birthday!! \u00e2\u009d\u00a4\u00ef\u00b8\u008f"
        }
      ],
      "title": "Tanaya Kamate wrote on your timeline."
    },
    {
      "timestamp": 1478625284,
      "data": [
        {
          "post": "Happy birthday"
        }
      ],
      "title": "Arun Singh wrote on your timeline."
    },
    {
      "timestamp": 1478604294,
      "data": [
        {
          "post": "Belated Happy birthday"
        }
      ],
      "title": "Sara Sabuwala wrote on your timeline."
    },
    {
      "timestamp": 1478578533,
      "data": [
        {
          "post": "Hbu"
        }
      ],
      "title": "Yash Shah wrote on your timeline."
    },
    {
      "timestamp": 1478575198,
      "data": [
        {
          "post": "Belated Happy Birthday"
        }
      ],
      "title": "Drigesh Mittal wrote on your timeline."
    },
    {
      "timestamp": 1478574348,
      "title": "Miteshan Agrawal wrote on your timeline."
    },
    {
      "timestamp": 1478520949,
      "title": "Rekha Menon wrote on your timeline."
    },
    {
      "timestamp": 1478515352,
      "data": [
        {
          "post": "many many happy returns of d day"
        }
      ],
      "title": "Purviish Shah wrote on your timeline."
    },
    {
      "timestamp": 1478515219,
      "data": [
        {
          "post": "Happy Birthday ..stay blessed.\u00f0\u009f\u0092\u0090\u00f0\u009f\u0092\u0090\u00f0\u009f\u008e\u0082"
        }
      ],
      "title": "Indu Nangia wrote on your timeline."
    },
    {
      "timestamp": 1478514485,
      "data": [
        {
          "post": "Appy bday dear"
        }
      ],
      "title": "Cma Manish wrote on your timeline."
    },
    {
      "timestamp": 1478511630,
      "data": [
        {
          "post": "Happy birthday!"
        }
      ],
      "title": "Akshay Patil wrote on your timeline."
    },
    {
      "timestamp": 1478505241,
      "data": [
        {
          "post": "Happy birthday :-)"
        }
      ],
      "title": "Ritu Agrawal Gupta wrote on your timeline."
    },
    {
      "timestamp": 1478502370,
      "data": [
        {
          "post": "Happy bday dear shubhanshi\u00f0\u009f\u008e\u0082"
        }
      ],
      "title": "Soniya Jain wrote on your timeline."
    },
    {
      "timestamp": 1478497802,
      "data": [
        {
          "post": "Happy bday!"
        }
      ],
      "title": "Jash Savla wrote on your timeline."
    },
    {
      "timestamp": 1478497122,
      "data": [
        {
          "post": "Happy Birthday"
        }
      ],
      "title": "Parth Samant wrote on your timeline."
    },
    {
      "timestamp": 1478495289,
      "data": [
        {
          "post": "Happy birthday my dear love you \u00f0\u009f\u008d\u00b0\u00f0\u009f\u0098\u0098\u00f0\u009f\u0098\u0098"
        }
      ],
      "title": "Shalu Goel wrote on your timeline."
    },
    {
      "timestamp": 1478492978,
      "data": [
        {
          "post": "Happy Birthday Shubhanshi"
        }
      ],
      "title": "Ashutosh Welankar wrote on your timeline."
    },
    {
      "timestamp": 1478492387,
      "title": "Amar Parab wrote on your timeline."
    },
    {
      "timestamp": 1446919689,
      "data": [
        {
          "post": "Happy birthday subhanshi..."
        }
      ],
      "title": "Kamlesh Agrawal wrote on your timeline."
    },
    {
      "timestamp": 1446918489,
      "data": [
        {
          "post": "Happy bday.... ."
        }
      ],
      "title": "Nicks Jain wrote on your timeline."
    },
    {
      "timestamp": 1446911005,
      "data": [
        {
          "post": "Happy Birthday bache..stay blessed :* :*"
        }
      ],
      "title": "Indu Nangia wrote on your timeline."
    },
    {
      "timestamp": 1446910323,
      "data": [
        {
          "post": "Happy bday dear"
        }
      ],
      "title": "Ketav Savant wrote on your timeline."
    },
    {
      "timestamp": 1446908106,
      "data": [
        {
          "post": "Happy birthday!"
        }
      ],
      "title": "Parth Samant wrote on your timeline."
    },
    {
      "timestamp": 1446904511,
      "data": [
        {
          "post": "HBD Shubhanshi"
        }
      ],
      "title": "Ashutosh Welankar wrote on your timeline."
    },
    {
      "timestamp": 1446895079,
      "data": [
        {
          "post": "Happy Birthday \u00f3\u00be\u008c\u00b8\u00f3\u00be\u0094\u0097\u00f3\u00be\u0094\u0091"
        }
      ],
      "title": "Virali Modi wrote on your timeline."
    },
    {
      "timestamp": 1446892459,
      "data": [
        {
          "post": "Happy birthday to you"
        }
      ],
      "title": "Yash Shah wrote on your timeline."
    },
    {
      "timestamp": 1446890158,
      "data": [
        {
          "post": "Happy birthday"
        }
      ],
      "title": "Aakash Mahajan wrote on your timeline."
    },
    {
      "timestamp": 1446888790,
      "data": [
        {
          "post": "Happy birthday to subhanshi...."
        }
      ],
      "title": "Arun Jain wrote on your timeline."
    },
    {
      "timestamp": 1446887128,
      "data": [
        {
          "post": "Happy birthday :-)"
        }
      ],
      "title": "Ritu Agrawal Gupta wrote on your timeline."
    },
    {
      "timestamp": 1446884803,
      "data": [
        {
          "post": "Happy birthday"
        }
      ],
      "title": "Saniya Mehta wrote on your timeline."
    },
    {
      "timestamp": 1446883482,
      "data": [
        {
          "post": "Happy bday"
        }
      ],
      "title": "Punit Patel wrote on your timeline."
    },
    {
      "timestamp": 1446878815,
      "data": [
        {
          "post": "Happy Birthday Shubhanshi\u00f3\u00be\u008c\u00b3"
        }
      ],
      "title": "Rohit Dongre wrote on your timeline."
    },
    {
      "timestamp": 1446878349,
      "data": [
        {
          "post": "Happy birthday"
        }
      ],
      "title": "Aditya Anil Chavan wrote on your timeline."
    },
    {
      "timestamp": 1446877990,
      "data": [
        {
          "post": "Happy Birthdayy. :D"
        }
      ],
      "title": "Rohan Karnik wrote on your timeline."
    },
    {
      "timestamp": 1446877189,
      "data": [
        {
          "post": "Happy birthday \u00f3\u00be\u00a6\u0083"
        }
      ],
      "title": "Adit Parghi wrote on your timeline."
    },
    {
      "timestamp": 1446875900,
      "data": [
        {
          "post": "Happy birthday \u00f3\u00be\u0086\u0093\u00f3\u00be\u008d\u0091\u00f0\u009f\u008f\u00bc"
        }
      ],
      "title": "Anuj Singh Thakur wrote on your timeline."
    },
    {
      "timestamp": 1446874394,
      "data": [
        {
          "post": "Happy bday \u00f3\u00be\u008c\u00a7\u00f3\u00be\u008c\u00a7\u00f3\u00be\u008c\u00ac"
        }
      ],
      "title": "Diya Kadri wrote on your timeline."
    },
    {
      "timestamp": 1446873510,
      "data": [
        {
          "post": "Appy bday dear"
        }
      ],
      "title": "Cma Manish wrote on your timeline."
    },
    {
      "timestamp": 1446872720,
      "data": [
        {
          "post": "Happy birthday !!!!!!!!"
        }
      ],
      "title": "Keshav Sathe wrote on your timeline."
    },
    {
      "timestamp": 1446872283,
      "data": [
        {
          "post": "Happy birthday !"
        }
      ],
      "title": "Harshwardhan Dadhich wrote on your timeline."
    },
    {
      "timestamp": 1446871840,
      "data": [
        {
          "post": "Happy b'dae"
        }
      ],
      "title": "Sahil Gosavi wrote on your timeline."
    },
    {
      "timestamp": 1446871536,
      "data": [
        {
          "post": "Happy birthday:-)"
        }
      ],
      "title": "Akshi Shetty wrote on your timeline."
    },
    {
      "timestamp": 1446870785,
      "data": [
        {
          "post": "Happiest birthday Shubhansi"
        }
      ],
      "title": "Keyul Mer wrote on your timeline."
    },
    {
      "timestamp": 1446869704,
      "data": [
        {
          "post": "Happy birthday"
        }
      ],
      "title": "Advait Savant wrote on your timeline."
    },
    {
      "timestamp": 1446865355,
      "data": [
        {
          "post": "Happpppy wala bday!"
        }
      ],
      "title": "Madhunandan Jayaram wrote on your timeline."
    },
    {
      "timestamp": 1446864246,
      "data": [
        {
          "post": "many many happy returns of d day"
        }
      ],
      "title": "Purviish Shah wrote on your timeline."
    },
    {
      "timestamp": 1418546220,
      "data": [
        {
          "post": "happy birthday shubhanshi :*"
        }
      ],
      "title": "Riya Kothari wrote on your timeline."
    },
    {
      "timestamp": 1416990466,
      "data": [
        {
          "post": "Happie bdae.!"
        }
      ],
      "title": "Param Vora wrote on your timeline."
    },
    {
      "timestamp": 1415384116,
      "data": [
        {
          "post": "happy birthday!! :p\nenjoy :)"
        }
      ],
      "title": "Rahul Chopra wrote on your timeline."
    },
    {
      "timestamp": 1415380709,
      "data": [
        {
          "post": "Happy Birthday"
        }
      ],
      "title": "Janki Tikekar wrote on your timeline."
    },
    {
      "timestamp": 1415376718,
      "data": [
        {
          "post": "Happy B'daee 2 u!!!!! Have a blast!!!! :P"
        }
      ],
      "title": "Preet Khandawala wrote on your timeline."
    },
    {
      "timestamp": 1415376308,
      "data": [
        {
          "post": "Happy Birthday....."
        }
      ],
      "title": "Drigesh Mittal wrote on your timeline."
    },
    {
      "timestamp": 1415375685,
      "data": [
        {
          "post": "hbd  :)"
        }
      ],
      "title": "Gauri Lad wrote on your timeline."
    },
    {
      "timestamp": 1415371712,
      "data": [
        {
          "post": "HBD!"
        }
      ],
      "title": "Pranay Ranka wrote on your timeline."
    },
    {
      "timestamp": 1415361738,
      "data": [
        {
          "post": "happy bday"
        }
      ],
      "title": "Mahima Somani wrote on your timeline."
    },
    {
      "timestamp": 1415359301,
      "data": [
        {
          "post": "Happie bdae.!"
        }
      ],
      "title": "Param Vora wrote on your timeline."
    },
    {
      "timestamp": 1415358726,
      "data": [
        {
          "post": "happy bday shubhanshi"
        }
      ],
      "title": "Jadu Goel wrote on your timeline."
    },
    {
      "timestamp": 1415355354,
      "data": [
        {
          "post": "Many happy returns of the day -HAPPY BIRTHDAY"
        }
      ],
      "title": "Kiran Gupta wrote on your timeline."
    },
    {
      "timestamp": 1415354931,
      "data": [
        {
          "post": "Happy b day"
        }
      ],
      "title": "Soniya Jain wrote on your timeline."
    },
    {
      "timestamp": 1415354580,
      "data": [
        {
          "post": "Happyy birthdayy Shubhanshi Jain....parttyy hard :-D :-D"
        }
      ],
      "title": "Naman Chandak wrote on your timeline."
    },
    {
      "timestamp": 1415350847,
      "data": [
        {
          "post": "Happy birthday \n#enjoy"
        }
      ],
      "title": "Anvsh Ali wrote on your timeline."
    },
    {
      "timestamp": 1415347517,
      "data": [
        {
          "post": "Happy Birthday Shubhanshi\u00f3\u00be\u008c\u00b3"
        }
      ],
      "title": "Rohit Dongre wrote on your timeline."
    },
    {
      "timestamp": 1415346529,
      "data": [
        {
          "post": "Hbd"
        }
      ],
      "title": "Darshan Shah wrote on your timeline."
    },
    {
      "timestamp": 1415343362,
      "data": [
        {
          "post": "Happy birthday beta...stay blessed always :*"
        }
      ],
      "title": "Indu Nangia wrote on your timeline."
    },
    {
      "timestamp": 1415341938,
      "data": [
        {
          "post": "Happy Birthday :D"
        }
      ],
      "title": "Shantanu Nayak wrote on your timeline."
    },
    {
      "timestamp": 1415340251,
      "data": [
        {
          "post": "Happy b'day!"
        }
      ],
      "title": "Rushikesh Patel wrote on your timeline."
    },
    {
      "timestamp": 1415337043,
      "data": [
        {
          "post": "Happy birthday!! Stay blessed"
        }
      ],
      "title": "Joshua Kevin wrote on your timeline."
    },
    {
      "timestamp": 1415336930,
      "data": [
        {
          "post": "Happy Birthday"
        }
      ],
      "title": "Janki Tikekar wrote on your timeline."
    },
    {
      "timestamp": 1415336372,
      "data": [
        {
          "post": "Happy b'dae"
        }
      ],
      "title": "Smit Shah wrote on your timeline."
    },
    {
      "timestamp": 1415335769,
      "data": [
        {
          "post": "HBD!!!!!!!!!!!!!"
        }
      ],
      "title": "Kunal Shetye wrote on your timeline."
    },
    {
      "timestamp": 1415335510,
      "data": [
        {
          "post": "HBD SHUBHANSHI!"
        }
      ],
      "title": "Yash Joshi wrote on your timeline."
    },
    {
      "timestamp": 1415334411,
      "data": [
        {
          "post": "Happy b'day!!"
        }
      ],
      "title": "Sahil Kothari wrote on your timeline."
    },
    {
      "timestamp": 1415334403,
      "data": [
        {
          "post": "Many many happy returns of the day"
        }
      ],
      "title": "Ketav Savant wrote on your timeline."
    },
    {
      "timestamp": 1415334322,
      "data": [
        {
          "post": "Happy birthday..!"
        }
      ],
      "title": "Sara Sabuwala wrote on your timeline."
    },
    {
      "timestamp": 1415333417,
      "data": [
        {
          "post": "HBD.....!!!!!"
        }
      ],
      "title": "Jainam Shah wrote on your timeline."
    },
    {
      "timestamp": 1415333188,
      "data": [
        {
          "post": "Happy birthday"
        }
      ],
      "title": "Sanket Shantaram Jadhav wrote on your timeline."
    },
    {
      "timestamp": 1415333003,
      "data": [
        {
          "post": "Happy bdae shubhanshi!"
        }
      ],
      "title": "Jash Savla wrote on your timeline."
    },
    {
      "timestamp": 1415332821,
      "data": [
        {
          "post": "Happy birthday shubu"
        }
      ],
      "title": "Anjana Nair wrote on your timeline."
    },
    {
      "timestamp": 1415332781,
      "data": [
        {
          "post": "Happy birthday..!!\u00f3\u00be\u00b0\u0080"
        }
      ],
      "title": "Tanaya Kamate wrote on your timeline."
    },
    {
      "timestamp": 1415332365,
      "data": [
        {
          "post": "Happy b'day"
        }
      ],
      "title": "Sherly Samant wrote on your timeline."
    },
    {
      "timestamp": 1415331221,
      "data": [
        {
          "post": "many many happy returns of the day"
        }
      ],
      "title": "Paras A Kadam wrote on your timeline."
    },
    {
      "timestamp": 1415331088,
      "data": [
        {
          "post": "Happy Birthday:)"
        }
      ],
      "title": "Rohan Karnik wrote on your timeline."
    },
    {
      "timestamp": 1415330320,
      "data": [
        {
          "post": "Many many happy returns of the day"
        }
      ],
      "title": "Purviish Shah wrote on your timeline."
    },
    {
      "timestamp": 1415330145,
      "data": [
        {
          "post": "Happy birthday :-)"
        }
      ],
      "title": "Ritu Agrawal Gupta wrote on your timeline."
    },
    {
      "timestamp": 1415330051,
      "data": [
        {
          "post": "Happy birthday shubhanshi \nhave an awesome year ahead!!"
        }
      ],
      "title": "Mehar Singh wrote on your timeline."
    },
    {
      "timestamp": 1415328824,
      "data": [
        {
          "post": "Happy Birthday! \\"
        }
      ],
      "title": "Siddhant Jagdale wrote on your timeline."
    },
    {
      "timestamp": 1415328554,
      "data": [
        {
          "post": "Happy birthday"
        }
      ],
      "title": "Yogesh Jadhav wrote on your timeline."
    },
    {
      "timestamp": 1415327677,
      "data": [
        {
          "post": "Happy birthday. ."
        }
      ],
      "title": "Akshi Shetty wrote on your timeline."
    },
    {
      "timestamp": 1415327625,
      "data": [
        {
          "post": "happies bday shubhanshi....hav a blast dear...May all ur problems last till ur resolutions"
        }
      ],
      "title": "Priyanka Rao wrote on your timeline."
    },
    {
      "timestamp": 1389283189,
      "data": [
        {
          "post": "Hai Shubhanshi,  I am your bua nani, don 't you know me?  God bless you"
        }
      ],
      "title": "Indu Mittal wrote on your timeline."
    },
    {
      "timestamp": 1383845005,
      "data": [
        {
          "post": "Happy Birthday ..stay blessed..:*"
        }
      ],
      "title": "Indu Nangia wrote on your timeline."
    },
    {
      "timestamp": 1383844134,
      "data": [
        {
          "post": "happybirthday"
        }
      ],
      "title": "Ashutosh Welankar wrote on your timeline."
    },
    {
      "timestamp": 1383843688,
      "data": [
        {
          "post": "Happy Birthday :-)"
        }
      ],
      "title": "Ritu Agrawal Gupta wrote on your timeline."
    },
    {
      "timestamp": 1383841768,
      "data": [
        {
          "post": "hapie b'day subhanshi...hav a blst..party hard!!!"
        }
      ],
      "title": "Rutvik Bhadra wrote on your timeline."
    },
    {
      "timestamp": 1383840882,
      "data": [
        {
          "post": "happy birthday"
        }
      ],
      "title": "Nihar Sardal wrote on your timeline."
    },
    {
      "timestamp": 1383834706,
      "data": [
        {
          "post": "hdb!!"
        }
      ],
      "title": "Shubham Pandya wrote on your timeline."
    },
    {
      "timestamp": 1383832628,
      "data": [
        {
          "post": "happy b'day"
        }
      ],
      "title": "Nishit Mistry wrote on your timeline."
    },
    {
      "timestamp": 1383828405,
      "data": [
        {
          "post": "happy brth dae!! :* "
        }
      ],
      "title": "Srushti Shah wrote on your timeline."
    },
    {
      "timestamp": 1383828274,
      "data": [
        {
          "post": "Happy bdae..!!!\n:D"
        }
      ],
      "title": "Khushboo Kejriwal wrote on your timeline."
    },
    {
      "timestamp": 1383826403,
      "data": [
        {
          "post": "Happy Bday :P"
        }
      ],
      "title": "Jay Bansal wrote on your timeline."
    },
    {
      "timestamp": 1383823719,
      "data": [
        {
          "post": "HBD ! Partty Harrd ! :)"
        }
      ],
      "title": "Jashvi S Shah wrote on your timeline."
    },
    {
      "timestamp": 1383822863,
      "data": [
        {
          "post": "happy bday!!"
        }
      ],
      "title": "Gaurav Shah wrote on your timeline."
    },
    {
      "timestamp": 1383821981,
      "data": [
        {
          "post": "happy bday"
        }
      ],
      "title": "Kanishka Maheshwari wrote on your timeline."
    },
    {
      "timestamp": 1383816975,
      "data": [
        {
          "post": "happy b'dae!!!"
        }
      ],
      "title": "Jash Savla wrote on your timeline."
    },
    {
      "timestamp": 1383814308,
      "data": [
        {
          "post": "happie b'dae !!"
        }
      ],
      "title": "Stuti Parikh wrote on your timeline."
    },
    {
      "timestamp": 1383810683,
      "data": [
        {
          "post": "Happy birthday!!!!!"
        }
      ],
      "title": "Pratik Jadhav wrote on your timeline."
    },
    {
      "timestamp": 1383809319,
      "data": [
        {
          "post": "Happy birth day beta may god bless you with all happiness of life"
        }
      ],
      "title": "Indu Mittal wrote on your timeline."
    },
    {
      "timestamp": 1383807137,
      "data": [
        {
          "post": "happy birthday ......"
        }
      ],
      "title": "Tinkle Patel wrote on your timeline."
    },
    {
      "timestamp": 1383806887,
      "data": [
        {
          "post": "happy birthday"
        }
      ],
      "title": "Sanil Desai wrote on your timeline."
    },
    {
      "timestamp": 1383806228,
      "data": [
        {
          "post": "happy bdae..!"
        }
      ],
      "title": "Nehal Haraniya wrote on your timeline."
    },
    {
      "timestamp": 1383806199,
      "data": [
        {
          "post": "happy bday..!!"
        }
      ],
      "title": "Rama Desai wrote on your timeline."
    },
    {
      "timestamp": 1383803089,
      "data": [
        {
          "post": " happy birthday"
        }
      ],
      "title": "Keyul Mer wrote on your timeline."
    },
    {
      "timestamp": 1383801155,
      "data": [
        {
          "post": "happy birthday"
        }
      ],
      "title": "Dhruvin Mer wrote on your timeline."
    },
    {
      "timestamp": 1383798851,
      "data": [
        {
          "post": "Happy b'day Shubhanshi Jain"
        }
      ],
      "title": "Priyanka Agrawal wrote on your timeline."
    },
    {
      "timestamp": 1383798423,
      "data": [
        {
          "post": "many many happy returns of the day"
        }
      ],
      "title": "Ketav Savant wrote on your timeline."
    },
    {
      "timestamp": 1383789738,
      "data": [
        {
          "post": "Happy bdae "
        }
      ],
      "title": "Yachika Jain wrote on your timeline."
    },
    {
      "timestamp": 1383788815,
      "data": [
        {
          "post": "Happy Birthday"
        }
      ],
      "title": "Anuj Saboo wrote on your timeline."
    },
    {
      "timestamp": 1383787871,
      "data": [
        {
          "post": "happy bdae dear"
        }
      ],
      "title": "Saloni Shingre wrote on your timeline."
    },
    {
      "timestamp": 1383771808,
      "data": [
        {
          "post": "happy birthday"
        }
      ],
      "title": "Dhruva Khanchandani wrote on your timeline."
    },
    {
      "timestamp": 1383764641,
      "data": [
        {
          "post": "Happy bdae..enjoy to d fullest!!"
        }
      ],
      "title": "Adarsh Prabhudesai wrote on your timeline."
    },
    {
      "timestamp": 1383763872,
      "data": [
        {
          "post": "Happy b dae....\nEnjoy! Party hard :) ;)"
        }
      ],
      "title": "Dhiraj Lamba wrote on your timeline."
    },
    {
      "timestamp": 1383763584,
      "data": [
        {
          "post": "happy b'day!!!"
        }
      ],
      "title": "Meet Bavishi wrote on your timeline."
    },
    {
      "timestamp": 1383763516,
      "data": [
        {
          "post": "Happy b'dae Shubhanshi :* (DORAEMON) :P"
        }
      ],
      "title": "Riya Kothari wrote on your timeline."
    },
    {
      "timestamp": 1383762925,
      "data": [
        {
          "post": "happy b'dae..!!!"
        }
      ],
      "title": "Bhakti Bagwe wrote on your timeline."
    },
    {
      "timestamp": 1310064512,
      "data": [
        {
          "post": "Hi dear how r u? how's your trip?"
        }
      ],
      "title": "Grishma Agrawal wrote on your timeline."
    },
    {
      "timestamp": 1306261525,
      "data": [
        {
          "post": "Hi,How r u dear? Ghar Jake Enjoy Kiya\r\n"
        }
      ],
      "title": "Grishma Agrawal wrote on your timeline."
    },
    {
      "timestamp": 1300981671,
      "data": [
        {
          "post": "are you mad"
        }
      ],
      "title": "Akshat Jain wrote on your timeline."
    },
    {
      "timestamp": 1289140576,
      "data": [
        {
          "post": "hey .............\nhappy birthday!!!!!!!!!!!!..\nhav a blast..njoi!.!!!!"
        }
      ],
      "title": "Roshni Suvarna wrote on your timeline."
    },
    {
      "timestamp": 1289127367,
      "data": [
        {
          "post": "happy birthday!!!....................................................nd enjoy yur day"
        }
      ],
      "title": "Dhwani Jain wrote on your timeline."
    },
    {
      "timestamp": 1289123184,
      "data": [
        {
          "post": "happy birthday !!!!"
        }
      ],
      "title": "Tanaya Kamate wrote on your timeline."
    }
  ]
}