{
  "videos": [
    {
      "uri": "videos/26766025_1561414960610635_586681971309019136_n_1561414913943973.mp4",
      "creation_timestamp": 1515649476,
      "media_metadata": {
        "video_metadata": {
          "title": "Friendversary Video with Ashwin",
          "upload_timestamp": 0,
          "upload_ip": "2401:db00:1110:50ca:face:0:7a:0"
        }
      },
      "thumbnail": {
        "uri": "videos/thumbnails/24551202_1559615024123962_8738919577204817920_n.jpg"
      },
      "comments": [
        {
          "timestamp": 1515687522,
          "comment": "Aee jethiya\u00f0\u009f\u0098\u0082\u00f0\u009f\u0098\u0082\u00f0\u009f\u0098\u0082\u00f0\u009f\u0098\u0082\u00f0\u009f\u0098\u008d",
          "author": "Ashwin Tantri"
        }
      ]
    },
    {
      "uri": "videos/22873626_2076534949123904_1053144788640989184_n_1489399937812138.mp4",
      "creation_timestamp": 1509180458,
      "media_metadata": {
        "video_metadata": {
          "title": "Friendversary Video with Rishabh",
          "upload_timestamp": 0,
          "upload_ip": "2401:db00:3020:b0f9:face:0:31:0"
        }
      },
      "thumbnail": {
        "uri": "videos/thumbnails/22741649_1485652848186847_3672223834380959744_n.jpg"
      },
      "comments": [
        {
          "timestamp": 1509190683,
          "comment": "Tu kya chahta hai mai likhu many yrs to go\u00f0\u009f\u0098\u0082\u00f0\u009f\u0098\u0082?",
          "author": "Rishabh Bhansali"
        },
        {
          "timestamp": 1509190749,
          "comment": "Nahi re \u00f0\u009f\u0098\u0082\u00f0\u009f\u0098\u0082\u00f0\u009f\u0098\u0082 aaj unfriend tu",
          "author": "Nitin Bhansali"
        },
        {
          "timestamp": 1509192475,
          "comment": "\u00f0\u009f\u0098\u0082\u00f0\u009f\u0098\u0082\u00f0\u009f\u0098\u0082",
          "author": "Rishabh Bhansali"
        },
        {
          "timestamp": 1509248705,
          "comment": "Aww",
          "author": "Ria Bhansali"
        }
      ]
    },
    {
      "uri": "videos/22077817_1560217747422296_7274961841011294208_n_1463298750422257.mp4",
      "creation_timestamp": 1506589475,
      "media_metadata": {
        "video_metadata": {
          "title": "Friendversary Video with Tanishq",
          "upload_timestamp": 0,
          "upload_ip": "2401:db00:1110:5015:face:0:1f:0"
        }
      },
      "thumbnail": {
        "uri": "videos/thumbnails/22053517_1460838940668238_3611655316514537472_n.jpg"
      }
    }
  ]
}