{
  "events_invited": [
    {
      "name": "Mumbai Comic Con 2017!",
      "start_timestamp": 1510378200,
      "end_timestamp": 1510497000
    },
    {
      "name": "SaRVAA Reunion 2017",
      "start_timestamp": 1504958400,
      "end_timestamp": 0
    },
    {
      "name": "T.O.S",
      "start_timestamp": 1477668600,
      "end_timestamp": 1477684800
    },
    {
      "name": "SaRVAA Reunion'16",
      "start_timestamp": 1471698000,
      "end_timestamp": 0
    },
    {
      "name": "The Secret Package",
      "start_timestamp": 1465810200,
      "end_timestamp": 1466944200
    },
    {
      "name": "Yellow Claw",
      "start_timestamp": 1462707000,
      "end_timestamp": 0
    },
    {
      "name": "AnkurRitu Wedding",
      "start_timestamp": 1449930600,
      "end_timestamp": 0
    },
    {
      "name": "SaRVAA - Reunion'15",
      "start_timestamp": 1439038800,
      "end_timestamp": 0
    },
    {
      "name": "Blog Burst - www.sarthakstudio.blogspot.com",
      "start_timestamp": 1381170600,
      "end_timestamp": 0
    },
    {
      "name": "Nav Ratri",
      "start_timestamp": 1380911400,
      "end_timestamp": 0
    },
    {
      "name": "YOU",
      "start_timestamp": 1372962600,
      "end_timestamp": 0
    },
    {
      "name": "reasults!!!!!!!xxxxxxx",
      "start_timestamp": 1320757200,
      "end_timestamp": 1320768000
    }
  ]
}